{  
    "mqtt":{
        "port":1883,
        "subscriptions":[  
            "lzig/pc socket",
            "lzig/lifx socket",
            "lzig/poster socket",
            "lzig/wifi mesh socket",
            "lzig/sonos front socket",
            "lzig/sonos rear socket",
            "lzig/living heat",
            "thread_tags/thingy01/env",
            "lzig/living heater weather",
            "lzig/bedroom heat",
            "lzig/bedroom weather",
            "lzig/bedroom heater weather",
            "lzig/kitchen heat",
            "lzig/kitchen weather",
            "lzig/kitchen heater weather",
            "lzig/bathroom heat",
            "thread_tags/thingy02/env",
            "lzig/bathroom heater weather",
            "lzig/office heat",
            "lzig/office heater weather",
            "lzig/office air"
         ],
        "publish" :true,
        "subscribe" :true
    },
    "log":{
        "logfile":{
            "default":"log/log (date).log"
        },
        "level":"info"
    }
}
